{
    "id": 64,
    "name": "龙子湖三层：西：限流",
    "seat_dict": {
        "203": "56284",
        "201": "56282",
        "199": "56280",
        "205": "56286",
        "207": "56288",
        "213": "56294",
        "211": "56292",
        "209": "56290",
        "215": "56296",
        "217": "56298",
        "71": "56146",
        "69": "56144",
        "67": "56142",
        "11": "56074",
        "9": "56072",
        "7": "56070",
        "73": "56148",
        "75": "56150",
        "77": "56152",
        "13": "56076",
        "15": "56078",
        "17": "56080",
        "1": "56059",
        "143": "56218",
        "141": "56216",
        "139": "56214",
        "83": "56158",
        "81": "56156",
        "79": "56154",
        "23": "56086",
        "21": "56084",
        "19": "56082",
        "145": "56220",
        "147": "56222",
        "149": "56224",
        "85": "56160",
        "87": "56162",
        "89": "56164",
        "25": "56088",
        "27": "56090",
        "29": "56092",
        "3": "56061",
        "155": "56230",
        "153": "56228",
        "151": "56226",
        "95": "56170",
        "93": "56168",
        "91": "56166",
        "35": "56098",
        "33": "56096",
        "31": "56094",
        "157": "56232",
        "159": "56234",
        "161": "56236",
        "97": "56172",
        "99": "56174",
        "101": "56176",
        "37": "56100",
        "39": "56102",
        "41": "56104",
        "5": "56063",
        "167": "56242",
        "165": "56240",
        "163": "56238",
        "107": "56182",
        "105": "56180",
        "103": "56178",
        "47": "56110",
        "45": "56108",
        "43": "56106",
        "169": "56244",
        "171": "56246",
        "173": "56248",
        "109": "56184",
        "111": "56186",
        "113": "56188",
        "49": "56112",
        "51": "56114",
        "53": "56116",
        "179": "56255",
        "177": "56253",
        "175": "56250",
        "119": "56194",
        "117": "56192",
        "115": "56190",
        "59": "56122",
        "57": "56120",
        "55": "56118",
        "181": "56257",
        "183": "56259",
        "185": "56261",
        "121": "56196",
        "123": "56198",
        "125": "56200",
        "61": "56124",
        "63": "56126",
        "65": "56128",
        "191": "56267",
        "189": "56265",
        "187": "56263",
        "131": "56206",
        "129": "56204",
        "127": "56202",
        "193": "56269",
        "195": "56271",
        "197": "56273",
        "133": "56208",
        "135": "56210",
        "137": "56212"
    }
}